JavaMianshiZhengliJavaZhuanlanFix1/README.md
JavaMianshiZhengliJavaZhuanlanFix1/__init__.py
JavaMianshiZhengliJavaZhuanlanFix1/__main__.py
JavaMianshiZhengliJavaZhuanlanFix1/file.epub
JavaMianshiZhengliJavaZhuanlanFix1/index.html
JavaMianshiZhengliJavaZhuanlanFix1/css/__init__.py
JavaMianshiZhengliJavaZhuanlanFix1/css/annotations.css
JavaMianshiZhengliJavaZhuanlanFix1/css/main.css
JavaMianshiZhengliJavaZhuanlanFix1/css/normalize.css
JavaMianshiZhengliJavaZhuanlanFix1/css/popup.css
JavaMianshiZhengliJavaZhuanlanFix1/font/__init__.py
JavaMianshiZhengliJavaZhuanlanFix1/font/fontello.eot
JavaMianshiZhengliJavaZhuanlanFix1/font/fontello.svg
JavaMianshiZhengliJavaZhuanlanFix1/font/fontello.ttf
JavaMianshiZhengliJavaZhuanlanFix1/font/fontello.woff
JavaMianshiZhengliJavaZhuanlanFix1/img/__init__.py
JavaMianshiZhengliJavaZhuanlanFix1/img/annotator-glyph-sprite.png
JavaMianshiZhengliJavaZhuanlanFix1/img/annotator-icon-sprite.png
JavaMianshiZhengliJavaZhuanlanFix1/img/apple-touch-icon.png
JavaMianshiZhengliJavaZhuanlanFix1/img/cancelfullscreen.png
JavaMianshiZhengliJavaZhuanlanFix1/img/close.png
JavaMianshiZhengliJavaZhuanlanFix1/img/fullscreen.png
JavaMianshiZhengliJavaZhuanlanFix1/img/loader.gif
JavaMianshiZhengliJavaZhuanlanFix1/img/menu-icon.png
JavaMianshiZhengliJavaZhuanlanFix1/img/save.png
JavaMianshiZhengliJavaZhuanlanFix1/img/saved.png
JavaMianshiZhengliJavaZhuanlanFix1/img/settings-s.png
JavaMianshiZhengliJavaZhuanlanFix1/img/settings.png
JavaMianshiZhengliJavaZhuanlanFix1/img/star.png
JavaMianshiZhengliJavaZhuanlanFix1/js/__init__.py
JavaMianshiZhengliJavaZhuanlanFix1/js/epub.js
JavaMianshiZhengliJavaZhuanlanFix1/js/epub.min.js
JavaMianshiZhengliJavaZhuanlanFix1/js/epub.min.map
JavaMianshiZhengliJavaZhuanlanFix1/js/hooks.min.js
JavaMianshiZhengliJavaZhuanlanFix1/js/hooks.min.map
JavaMianshiZhengliJavaZhuanlanFix1/js/reader.js
JavaMianshiZhengliJavaZhuanlanFix1/js/reader.js.map
JavaMianshiZhengliJavaZhuanlanFix1/js/reader.min.js
java_mianshi_zhengli_java_zhuanlan_fix1-2025.3.24.0.dist-info/METADATA
java_mianshi_zhengli_java_zhuanlan_fix1-2025.3.24.0.dist-info/WHEEL
java_mianshi_zhengli_java_zhuanlan_fix1-2025.3.24.0.dist-info/entry_points.txt
java_mianshi_zhengli_java_zhuanlan_fix1-2025.3.24.0.dist-info/top_level.txt
java_mianshi_zhengli_java_zhuanlan_fix1-2025.3.24.0.dist-info/RECORD
